.gitignore
.travis.yml
AUTHORS
INSTALL.txt
LICENSE
MANIFEST.in
README.md
README.rst
requirements.txt
setup.py
test.sh
test_jinja.py
axado.pyjade.egg-info/PKG-INFO
axado.pyjade.egg-info/SOURCES.txt
axado.pyjade.egg-info/dependency_links.txt
axado.pyjade.egg-info/entry_points.txt
axado.pyjade.egg-info/requires.txt
axado.pyjade.egg-info/top_level.txt
examples/django_example/__init__.py
examples/django_example/manage.py
examples/django_example/settings.py
examples/django_example/urls.py
examples/django_example/templates/test.jade
examples/flask/run.py
examples/flask/templates/hello.jade
pyjade/__init__.py
pyjade/compiler.py
pyjade/convert.py
pyjade/exceptions.py
pyjade/filters.py
pyjade/lexer.py
pyjade/nodes.py
pyjade/parser.py
pyjade/runtime.py
pyjade/utils.py
pyjade/ext/__init__.py
pyjade/ext/html.py
pyjade/ext/jinja.py
pyjade/ext/mako.py
pyjade/ext/underscore.py
pyjade/ext/django/__init__.py
pyjade/ext/django/compiler.py
pyjade/ext/django/loader.py
pyjade/ext/django/templatetags.py
pyjade/ext/pyramid/__init__.py
pyjade/ext/tornado/__init__.py
pyjade/testsuite/test_cases.py
pyjade/testsuite/test_inline_lexer.py
pyjade/testsuite/test_runtime.py
pyjade/testsuite/cases/_mixins.ijade
pyjade/testsuite/cases/attr-with-quotes.html
pyjade/testsuite/cases/attr-with-quotes.jade
pyjade/testsuite/cases/attrs.html
pyjade/testsuite/cases/attrs.jade
pyjade/testsuite/cases/attrs.js.html
pyjade/testsuite/cases/attrs.js.jade
pyjade/testsuite/cases/attrs.spaced.html
pyjade/testsuite/cases/attrs.spaced.jade
pyjade/testsuite/cases/basic.html
pyjade/testsuite/cases/basic.jade
pyjade/testsuite/cases/blanks.html
pyjade/testsuite/cases/blanks.jade
pyjade/testsuite/cases/block-Django.html
pyjade/testsuite/cases/block-Django.jade
pyjade/testsuite/cases/block-expansion.html
pyjade/testsuite/cases/block-expansion.jade
pyjade/testsuite/cases/block-expansion.shorthands.html
pyjade/testsuite/cases/block-expansion.shorthands.jade
pyjade/testsuite/cases/classes.html
pyjade/testsuite/cases/classes.jade
pyjade/testsuite/cases/code.conditionals.html
pyjade/testsuite/cases/code.conditionals.jade
pyjade/testsuite/cases/code.escape.html
pyjade/testsuite/cases/code.escape.jade
pyjade/testsuite/cases/code.html
