Metadata-Version: 1.0
Name: axado.pyjade
Version: 5.0.0
Summary: Jade syntax template adapter for Django, Jinja2, Mako and Tornado templates
Home-page: http://github.com/syrusakbary/pyjade
Author: Syrus Akbary
Author-email: me@syrusakbary.com
License: MIT
Keywords: jade template converter
Platform: UNKNOWN
